{
  "generated_at": "2026-01-10T16:03:37.164627",
  "game_date": "2026-01-09",
  "games": [
    {
      "game_id": 2025020694,
      "home_team": "CHI",
      "away_team": "WSH",
      "matchup": "WSH @ CHI",
      "players": [
        {
          "player_id": 8477479,
          "player_name": "Tyler Bertuzzi",
          "position": "L",
          "team": "CHI",
          "opponent": "WSH",
          "is_home": true,
          "expected_shots": 2.86,
          "shots_std": 1.64,
          "prob_2plus": 0.779,
          "prob_3plus": 0.544,
          "prob_4plus": 0.321,
          "confidence": 0.805,
          "avg_toi_minutes": 18.5,
          "games_analyzed": 15,
          "historical_avg_shots": 2.47,
          "deviation_from_avg": 0.39,
          "deviation_pct": 15.9,
          "variance_indicator": "Higher*",
          "injury_status": "",
          "injury_weight": 1.0,
          "actual_shots": null,
          "hit_2plus": null,
          "hit_3plus": null
        },
        {
          "player_id": 8483450,
          "player_name": "Ryan Greene",
          "position": "C",
          "team": "CHI",
          "opponent": "WSH",
          "is_home": true,
          "expected_shots": 2.16,
          "shots_std": 1.22,
          "prob_2plus": 0.634,
          "prob_3plus": 0.365,
          "prob_4plus": 0.172,
          "confidence": 0.801,
          "avg_toi_minutes": 17.3,
          "games_analyzed": 15,
          "historical_avg_shots": 1.73,
          "deviation_from_avg": 0.42,
          "deviation_pct": 24.3,
          "variance_indicator": "Higher*",
          "injury_status": "",
          "injury_weight": 1.0,
          "actual_shots": null,
          "hit_2plus": null,
          "hit_3plus": null
        },
        {
          "player_id": 8477444,
          "player_name": "Andre Burakovsky",
          "position": "L",
          "team": "CHI",
          "opponent": "WSH",
          "is_home": true,
          "expected_shots": 1.63,
          "shots_std": 1.45,
          "prob_2plus": 0.458,
          "prob_3plus": 0.234,
          "prob_4plus": 0.106,
          "confidence": 0.763,
          "avg_toi_minutes": 17.3,
          "games_analyzed": 15,
          "historical_avg_shots": 1.4,
          "deviation_from_avg": 0.23,
          "deviation_pct": 16.4,
          "variance_indicator": "Volatile",
          "injury_status": "",
          "injury_weight": 1.0,
          "actual_shots": null,
          "hit_2plus": null,
          "hit_3plus": null
        },
        {
          "player_id": 8481806,
          "player_name": "Louis Crevier",
          "position": "D",
          "team": "CHI",
          "opponent": "WSH",
          "is_home": true,
          "expected_shots": 1.62,
          "shots_std": 0.88,
          "prob_2plus": 0.482,
          "prob_3plus": 0.223,
          "prob_4plus": 0.082,
          "confidence": 0.573,
          "avg_toi_minutes": 18.1,
          "games_analyzed": 15,
          "historical_avg_shots": 1.93,
          "deviation_from_avg": -0.31,
          "deviation_pct": -16.0,
          "variance_indicator": "Lower*",
          "injury_status": "DTD",
          "injury_weight": 0.5,
          "actual_shots": null,
          "hit_2plus": null,
          "hit_3plus": null
        },
        {
          "player_id": 8477987,
          "player_name": "Ryan Donato",
          "position": "C",
          "team": "CHI",
          "opponent": "WSH",
          "is_home": true,
          "expected_shots": 1.57,
          "shots_std": 1.78,
          "prob_2plus": 0.397,
          "prob_3plus": 0.228,
          "prob_4plus": 0.128,
          "confidence": 0.754,
          "avg_toi_minutes": 15.8,
          "games_analyzed": 15,
          "historical_avg_shots": 1.53,
          "deviation_from_avg": 0.03,
          "deviation_pct": 2.2,
          "variance_indicator": "Volatile",
          "injury_status": "",
          "injury_weight": 1.0,
          "actual_shots": null,
          "hit_2plus": null,
          "hit_3plus": null
        },
        {
          "player_id": 8481624,
          "player_name": "Ilya Mikheyev",
          "position": "R",
          "team": "CHI",
          "opponent": "WSH",
          "is_home": true,
          "expected_shots": 1.54,
          "shots_std": 1.28,
          "prob_2plus": 0.449,
          "prob_3plus": 0.204,
          "prob_4plus": 0.076,
          "confidence": 0.54,
          "avg_toi_minutes": 17.2,
          "games_analyzed": 15,
          "historical_avg_shots": 1.73,
          "deviation_from_avg": -0.2,
          "deviation_pct": -11.3,
          "variance_indicator": "Volatile",
          "injury_status": "DTD",
          "injury_weight": 0.5,
          "actual_shots": null,
          "hit_2plus": null,
          "hit_3plus": null
        },
        {
          "player_id": 8476882,
          "player_name": "Teuvo Teravainen",
          "position": "C",
          "team": "CHI",
          "opponent": "WSH",
          "is_home": true,
          "expected_shots": 1.53,
          "shots_std": 0.99,
          "prob_2plus": 0.453,
          "prob_3plus": 0.199,
          "prob_4plus": 0.07,
          "confidence": 0.782,
          "avg_toi_minutes": 17.1,
          "games_analyzed": 15,
          "historical_avg_shots": 1.47,
          "deviation_from_avg": 0.07,
          "deviation_pct": 4.5,
          "variance_indicator": "Volatile",
          "injury_status": "",
          "injury_weight": 1.0,
          "actual_shots": null,
          "hit_2plus": null,
          "hit_3plus": null
        },
        {
          "player_id": 8479345,
          "player_name": "Jakob Chychrun",
          "position": "D",
          "team": "WSH",
          "opponent": "CHI",
          "is_home": false,
          "expected_shots": 2.65,
          "shots_std": 2.0,
          "prob_2plus": 0.678,
          "prob_3plus": 0.461,
          "prob_4plus": 0.286,
          "confidence": 0.774,
          "avg_toi_minutes": 23.2,
          "games_analyzed": 15,
          "historical_avg_shots": 3.47,
          "deviation_from_avg": -0.81,
          "deviation_pct": -23.5,
          "variance_indicator": "Volatile",
          "injury_status": "",
          "injury_weight": 1.0,
          "actual_shots": null,
          "hit_2plus": null,
          "hit_3plus": null
        },
        {
          "player_id": 8471214,
          "player_name": "Alex Ovechkin",
          "position": "L",
          "team": "WSH",
          "opponent": "CHI",
          "is_home": false,
          "expected_shots": 2.65,
          "shots_std": 1.52,
          "prob_2plus": 0.741,
          "prob_3plus": 0.493,
          "prob_4plus": 0.274,
          "confidence": 0.811,
          "avg_toi_minutes": 17.8,
          "games_analyzed": 15,
          "historical_avg_shots": 2.8,
          "deviation_from_avg": -0.15,
          "deviation_pct": -5.5,
          "variance_indicator": "Variable",
          "injury_status": "",
          "injury_weight": 1.0,
          "actual_shots": null,
          "hit_2plus": null,
          "hit_3plus": null
        },
        {
          "player_id": 8476880,
          "player_name": "Tom Wilson",
          "position": "R",
          "team": "WSH",
          "opponent": "CHI",
          "is_home": false,
          "expected_shots": 2.43,
          "shots_std": 2.51,
          "prob_2plus": 0.546,
          "prob_3plus": 0.377,
          "prob_4plus": 0.254,
          "confidence": 0.521,
          "avg_toi_minutes": 19.2,
          "games_analyzed": 15,
          "historical_avg_shots": 2.67,
          "deviation_from_avg": -0.24,
          "deviation_pct": -9.0,
          "variance_indicator": "Volatile",
          "injury_status": "DTD",
          "injury_weight": 0.5,
          "actual_shots": null,
          "hit_2plus": null,
          "hit_3plus": null
        },
        {
          "player_id": 8478440,
          "player_name": "Dylan Strome",
          "position": "C",
          "team": "WSH",
          "opponent": "CHI",
          "is_home": false,
          "expected_shots": 2.11,
          "shots_std": 1.11,
          "prob_2plus": 0.624,
          "prob_3plus": 0.354,
          "prob_4plus": 0.164,
          "confidence": 0.823,
          "avg_toi_minutes": 18.9,
          "games_analyzed": 15,
          "historical_avg_shots": 2.33,
          "deviation_from_avg": -0.22,
          "deviation_pct": -9.4,
          "variance_indicator": "Variable",
          "injury_status": "",
          "injury_weight": 1.0,
          "actual_shots": null,
          "hit_2plus": null,
          "hit_3plus": null
        },
        {
          "player_id": 8481656,
          "player_name": "Aliaksei Protas",
          "position": "C",
          "team": "WSH",
          "opponent": "CHI",
          "is_home": false,
          "expected_shots": 2.1,
          "shots_std": 1.52,
          "prob_2plus": 0.607,
          "prob_3plus": 0.349,
          "prob_4plus": 0.17,
          "confidence": 0.759,
          "avg_toi_minutes": 17.8,
          "games_analyzed": 15,
          "historical_avg_shots": 2.2,
          "deviation_from_avg": -0.1,
          "deviation_pct": -4.5,
          "variance_indicator": "Volatile",
          "injury_status": "",
          "injury_weight": 1.0,
          "actual_shots": null,
          "hit_2plus": null,
          "hit_3plus": null
        },
        {
          "player_id": 8484186,
          "player_name": "Ryan Leonard",
          "position": "R",
          "team": "WSH",
          "opponent": "CHI",
          "is_home": false,
          "expected_shots": 2.05,
          "shots_std": 1.66,
          "prob_2plus": 0.565,
          "prob_3plus": 0.333,
          "prob_4plus": 0.175,
          "confidence": 0.739,
          "avg_toi_minutes": 15.5,
          "games_analyzed": 15,
          "historical_avg_shots": 2.27,
          "deviation_from_avg": -0.22,
          "deviation_pct": -9.6,
          "variance_indicator": "Volatile",
          "injury_status": "",
          "injury_weight": 1.0,
          "actual_shots": null,
          "hit_2plus": null,
          "hit_3plus": null
        },
        {
          "player_id": 8478463,
          "player_name": "Anthony Beauvillier",
          "position": "L",
          "team": "WSH",
          "opponent": "CHI",
          "is_home": false,
          "expected_shots": 1.93,
          "shots_std": 1.39,
          "prob_2plus": 0.576,
          "prob_3plus": 0.305,
          "prob_4plus": 0.131,
          "confidence": 0.761,
          "avg_toi_minutes": 16.4,
          "games_analyzed": 15,
          "historical_avg_shots": 2.07,
          "deviation_from_avg": -0.13,
          "deviation_pct": -6.5,
          "variance_indicator": "Volatile",
          "injury_status": "",
          "injury_weight": 1.0,
          "actual_shots": null,
          "hit_2plus": null,
          "hit_3plus": null
        },
        {
          "player_id": 8482088,
          "player_name": "Justin Sourdif",
          "position": "R",
          "team": "WSH",
          "opponent": "CHI",
          "is_home": false,
          "expected_shots": 1.85,
          "shots_std": 1.23,
          "prob_2plus": 0.553,
          "prob_3plus": 0.284,
          "prob_4plus": 0.117,
          "confidence": 0.773,
          "avg_toi_minutes": 17.0,
          "games_analyzed": 15,
          "historical_avg_shots": 1.67,
          "deviation_from_avg": 0.19,
          "deviation_pct": 11.2,
          "variance_indicator": "Volatile",
          "injury_status": "",
          "injury_weight": 1.0,
          "actual_shots": null,
          "hit_2plus": null,
          "hit_3plus": null
        },
        {
          "player_id": 8481580,
          "player_name": "Connor McMichael",
          "position": "C",
          "team": "WSH",
          "opponent": "CHI",
          "is_home": false,
          "expected_shots": 1.66,
          "shots_std": 1.36,
          "prob_2plus": 0.485,
          "prob_3plus": 0.237,
          "prob_4plus": 0.097,
          "confidence": 0.764,
          "avg_toi_minutes": 18.1,
          "games_analyzed": 15,
          "historical_avg_shots": 1.47,
          "deviation_from_avg": 0.2,
          "deviation_pct": 13.5,
          "variance_indicator": "Volatile",
          "injury_status": "",
          "injury_weight": 1.0,
          "actual_shots": null,
          "hit_2plus": null,
          "hit_3plus": null
        }
      ]
    },
    {
      "game_id": 2025020696,
      "home_team": "UTA",
      "away_team": "STL",
      "matchup": "STL @ UTA",
      "players": [
        {
          "player_id": 8482699,
          "player_name": "Dylan Guenther",
          "position": "R",
          "team": "UTA",
          "opponent": "STL",
          "is_home": true,
          "expected_shots": 3.29,
          "shots_std": 1.74,
          "prob_2plus": 0.836,
          "prob_3plus": 0.639,
          "prob_4plus": 0.417,
          "confidence": 0.822,
          "avg_toi_minutes": 17.1,
          "games_analyzed": 15,
          "historical_avg_shots": 3.2,
          "deviation_from_avg": 0.09,
          "deviation_pct": 2.8,
          "variance_indicator": "Variable",
          "injury_status": "",
          "injury_weight": 1.0,
          "actual_shots": null,
          "hit_2plus": null,
          "hit_3plus": null
        },
        {
          "player_id": 8477951,
          "player_name": "Nick Schmaltz",
          "position": "C",
          "team": "UTA",
          "opponent": "STL",
          "is_home": true,
          "expected_shots": 2.9,
          "shots_std": 2.28,
          "prob_2plus": 0.691,
          "prob_3plus": 0.495,
          "prob_4plus": 0.33,
          "confidence": 0.775,
          "avg_toi_minutes": 20.3,
          "games_analyzed": 15,
          "historical_avg_shots": 2.73,
          "deviation_from_avg": 0.17,
          "deviation_pct": 6.3,
          "variance_indicator": "Volatile",
          "injury_status": "",
          "injury_weight": 1.0,
          "actual_shots": null,
          "hit_2plus": null,
          "hit_3plus": null
        },
        {
          "player_id": 8479343,
          "player_name": "Clayton Keller",
          "position": "R",
          "team": "UTA",
          "opponent": "STL",
          "is_home": true,
          "expected_shots": 2.43,
          "shots_std": 1.19,
          "prob_2plus": 0.698,
          "prob_3plus": 0.438,
          "prob_4plus": 0.228,
          "confidence": 0.832,
          "avg_toi_minutes": 20.3,
          "games_analyzed": 15,
          "historical_avg_shots": 2.47,
          "deviation_from_avg": -0.04,
          "deviation_pct": -1.4,
          "variance_indicator": "Variable",
          "injury_status": "",
          "injury_weight": 1.0,
          "actual_shots": null,
          "hit_2plus": null,
          "hit_3plus": null
        },
        {
          "player_id": 8482175,
          "player_name": "JJ Peterka",
          "position": "R",
          "team": "UTA",
          "opponent": "STL",
          "is_home": true,
          "expected_shots": 2.09,
          "shots_std": 2.49,
          "prob_2plus": 0.463,
          "prob_3plus": 0.311,
          "prob_4plus": 0.209,
          "confidence": 0.752,
          "avg_toi_minutes": 17.9,
          "games_analyzed": 15,
          "historical_avg_shots": 2.07,
          "deviation_from_avg": 0.02,
          "deviation_pct": 1.0,
          "variance_indicator": "Volatile",
          "injury_status": "",
          "injury_weight": 1.0,
          "actual_shots": null,
          "hit_2plus": null,
          "hit_3plus": null
        },
        {
          "player_id": 8479410,
          "player_name": "Mikhail Sergachev",
          "position": "D",
          "team": "UTA",
          "opponent": "STL",
          "is_home": true,
          "expected_shots": 1.94,
          "shots_std": 1.16,
          "prob_2plus": 0.577,
          "prob_3plus": 0.307,
          "prob_4plus": 0.132,
          "confidence": 0.803,
          "avg_toi_minutes": 23.9,
          "games_analyzed": 15,
          "historical_avg_shots": 2.07,
          "deviation_from_avg": -0.13,
          "deviation_pct": -6.2,
          "variance_indicator": "Volatile",
          "injury_status": "",
          "injury_weight": 1.0,
          "actual_shots": null,
          "hit_2plus": null,
          "hit_3plus": null
        },
        {
          "player_id": 8480434,
          "player_name": "Sean Durzi",
          "position": "D",
          "team": "UTA",
          "opponent": "STL",
          "is_home": true,
          "expected_shots": 1.82,
          "shots_std": 1.16,
          "prob_2plus": 0.544,
          "prob_3plus": 0.276,
          "prob_4plus": 0.113,
          "confidence": 0.789,
          "avg_toi_minutes": 20.9,
          "games_analyzed": 15,
          "historical_avg_shots": 2.07,
          "deviation_from_avg": -0.24,
          "deviation_pct": -11.8,
          "variance_indicator": "Volatile",
          "injury_status": "",
          "injury_weight": 1.0,
          "actual_shots": null,
          "hit_2plus": null,
          "hit_3plus": null
        },
        {
          "player_id": 8478474,
          "player_name": "Lawson Crouse",
          "position": "L",
          "team": "UTA",
          "opponent": "STL",
          "is_home": true,
          "expected_shots": 1.65,
          "shots_std": 1.3,
          "prob_2plus": 0.488,
          "prob_3plus": 0.231,
          "prob_4plus": 0.088,
          "confidence": 0.77,
          "avg_toi_minutes": 17.3,
          "games_analyzed": 15,
          "historical_avg_shots": 1.47,
          "deviation_from_avg": 0.18,
          "deviation_pct": 12.5,
          "variance_indicator": "Volatile",
          "injury_status": "",
          "injury_weight": 1.0,
          "actual_shots": null,
          "hit_2plus": null,
          "hit_3plus": null
        },
        {
          "player_id": 8480849,
          "player_name": "Barrett Hayton",
          "position": "C",
          "team": "UTA",
          "opponent": "STL",
          "is_home": true,
          "expected_shots": 1.62,
          "shots_std": 1.99,
          "prob_2plus": 0.39,
          "prob_3plus": 0.237,
          "prob_4plus": 0.144,
          "confidence": 0.774,
          "avg_toi_minutes": 14.6,
          "games_analyzed": 15,
          "historical_avg_shots": 1.67,
          "deviation_from_avg": -0.05,
          "deviation_pct": -2.8,
          "variance_indicator": "Volatile",
          "injury_status": "",
          "injury_weight": 1.0,
          "actual_shots": null,
          "hit_2plus": null,
          "hit_3plus": null
        },
        {
          "player_id": 8479385,
          "player_name": "Jordan Kyrou",
          "position": "R",
          "team": "STL",
          "opponent": "UTA",
          "is_home": false,
          "expected_shots": 1.56,
          "shots_std": 1.65,
          "prob_2plus": 0.409,
          "prob_3plus": 0.225,
          "prob_4plus": 0.118,
          "confidence": 0.73,
          "avg_toi_minutes": 14.6,
          "games_analyzed": 15,
          "historical_avg_shots": 2.2,
          "deviation_from_avg": -0.64,
          "deviation_pct": -29.2,
          "variance_indicator": "Volatile",
          "injury_status": "",
          "injury_weight": 1.0,
          "actual_shots": null,
          "hit_2plus": null,
          "hit_3plus": null
        }
      ]
    },
    {
      "game_id": 2025020695,
      "home_team": "WPG",
      "away_team": "LAK",
      "matchup": "LAK @ WPG",
      "players": [
        {
          "player_id": 8478398,
          "player_name": "Kyle Connor",
          "position": "L",
          "team": "WPG",
          "opponent": "LAK",
          "is_home": true,
          "expected_shots": 2.25,
          "shots_std": 2.2,
          "prob_2plus": 0.543,
          "prob_3plus": 0.358,
          "prob_4plus": 0.227,
          "confidence": 0.77,
          "avg_toi_minutes": 21.6,
          "games_analyzed": 15,
          "historical_avg_shots": 3.47,
          "deviation_from_avg": -1.21,
          "deviation_pct": -35.0,
          "variance_indicator": "Volatile",
          "injury_status": "",
          "injury_weight": 1.0,
          "actual_shots": null,
          "hit_2plus": null,
          "hit_3plus": null
        },
        {
          "player_id": 8476460,
          "player_name": "Mark Scheifele",
          "position": "C",
          "team": "WPG",
          "opponent": "LAK",
          "is_home": true,
          "expected_shots": 1.62,
          "shots_std": 2.13,
          "prob_2plus": 0.375,
          "prob_3plus": 0.235,
          "prob_4plus": 0.148,
          "confidence": 0.767,
          "avg_toi_minutes": 21.9,
          "games_analyzed": 15,
          "historical_avg_shots": 2.13,
          "deviation_from_avg": -0.51,
          "deviation_pct": -24.0,
          "variance_indicator": "Volatile",
          "injury_status": "",
          "injury_weight": 1.0,
          "actual_shots": null,
          "hit_2plus": null,
          "hit_3plus": null
        },
        {
          "player_id": 8477960,
          "player_name": "Adrian Kempe",
          "position": "R",
          "team": "LAK",
          "opponent": "WPG",
          "is_home": false,
          "expected_shots": 2.37,
          "shots_std": 1.77,
          "prob_2plus": 0.642,
          "prob_3plus": 0.407,
          "prob_4plus": 0.23,
          "confidence": 0.766,
          "avg_toi_minutes": 18.6,
          "games_analyzed": 15,
          "historical_avg_shots": 2.47,
          "deviation_from_avg": -0.1,
          "deviation_pct": -4.1,
          "variance_indicator": "Volatile",
          "injury_status": "",
          "injury_weight": 1.0,
          "actual_shots": null,
          "hit_2plus": null,
          "hit_3plus": null
        },
        {
          "player_id": 8477942,
          "player_name": "Kevin Fiala",
          "position": "L",
          "team": "LAK",
          "opponent": "WPG",
          "is_home": false,
          "expected_shots": 2.35,
          "shots_std": 1.19,
          "prob_2plus": 0.681,
          "prob_3plus": 0.418,
          "prob_4plus": 0.212,
          "confidence": 0.827,
          "avg_toi_minutes": 18.6,
          "games_analyzed": 15,
          "historical_avg_shots": 2.47,
          "deviation_from_avg": -0.11,
          "deviation_pct": -4.6,
          "variance_indicator": "Variable",
          "injury_status": "",
          "injury_weight": 1.0,
          "actual_shots": null,
          "hit_2plus": null,
          "hit_3plus": null
        },
        {
          "player_id": 8482155,
          "player_name": "Alex Laferriere",
          "position": "R",
          "team": "LAK",
          "opponent": "WPG",
          "is_home": false,
          "expected_shots": 2.33,
          "shots_std": 2.12,
          "prob_2plus": 0.576,
          "prob_3plus": 0.379,
          "prob_4plus": 0.237,
          "confidence": 0.772,
          "avg_toi_minutes": 17.3,
          "games_analyzed": 15,
          "historical_avg_shots": 2.93,
          "deviation_from_avg": -0.6,
          "deviation_pct": -20.5,
          "variance_indicator": "Volatile",
          "injury_status": "",
          "injury_weight": 1.0,
          "actual_shots": null,
          "hit_2plus": null,
          "hit_3plus": null
        },
        {
          "player_id": 8477998,
          "player_name": "Warren Foegele",
          "position": "L",
          "team": "LAK",
          "opponent": "WPG",
          "is_home": false,
          "expected_shots": 1.97,
          "shots_std": 1.82,
          "prob_2plus": 0.517,
          "prob_3plus": 0.311,
          "prob_4plus": 0.175,
          "confidence": 0.771,
          "avg_toi_minutes": 15.2,
          "games_analyzed": 15,
          "historical_avg_shots": 2.2,
          "deviation_from_avg": -0.23,
          "deviation_pct": -10.4,
          "variance_indicator": "Volatile",
          "injury_status": "",
          "injury_weight": 1.0,
          "actual_shots": null,
          "hit_2plus": null,
          "hit_3plus": null
        },
        {
          "player_id": 8482124,
          "player_name": "Quinton Byfield",
          "position": "R",
          "team": "LAK",
          "opponent": "WPG",
          "is_home": false,
          "expected_shots": 1.7,
          "shots_std": 1.33,
          "prob_2plus": 0.503,
          "prob_3plus": 0.246,
          "prob_4plus": 0.098,
          "confidence": 0.773,
          "avg_toi_minutes": 19.7,
          "games_analyzed": 15,
          "historical_avg_shots": 1.93,
          "deviation_from_avg": -0.23,
          "deviation_pct": -11.8,
          "variance_indicator": "Volatile",
          "injury_status": "",
          "injury_weight": 1.0,
          "actual_shots": null,
          "hit_2plus": null,
          "hit_3plus": null
        },
        {
          "player_id": 8474563,
          "player_name": "Drew Doughty",
          "position": "D",
          "team": "LAK",
          "opponent": "WPG",
          "is_home": false,
          "expected_shots": 1.6,
          "shots_std": 1.36,
          "prob_2plus": 0.462,
          "prob_3plus": 0.223,
          "prob_4plus": 0.092,
          "confidence": 0.779,
          "avg_toi_minutes": 23.1,
          "games_analyzed": 15,
          "historical_avg_shots": 1.87,
          "deviation_from_avg": -0.27,
          "deviation_pct": -14.3,
          "variance_indicator": "Volatile",
          "injury_status": "",
          "injury_weight": 1.0,
          "actual_shots": null,
          "hit_2plus": null,
          "hit_3plus": null
        },
        {
          "player_id": 8482730,
          "player_name": "Brandt Clarke",
          "position": "D",
          "team": "LAK",
          "opponent": "WPG",
          "is_home": false,
          "expected_shots": 1.58,
          "shots_std": 1.58,
          "prob_2plus": 0.425,
          "prob_3plus": 0.228,
          "prob_4plus": 0.115,
          "confidence": 0.769,
          "avg_toi_minutes": 18.4,
          "games_analyzed": 15,
          "historical_avg_shots": 1.93,
          "deviation_from_avg": -0.35,
          "deviation_pct": -18.2,
          "variance_indicator": "Volatile",
          "injury_status": "",
          "injury_weight": 1.0,
          "actual_shots": null,
          "hit_2plus": null,
          "hit_3plus": null
        }
      ]
    }
  ],
  "all_predictions": [
    {
      "player_id": 8477479,
      "player_name": "Tyler Bertuzzi",
      "position": "L",
      "team": "CHI",
      "opponent": "WSH",
      "is_home": true,
      "expected_shots": 2.86,
      "shots_std": 1.64,
      "prob_2plus": 0.779,
      "prob_3plus": 0.544,
      "prob_4plus": 0.321,
      "confidence": 0.805,
      "avg_toi_minutes": 18.5,
      "games_analyzed": 15,
      "historical_avg_shots": 2.47,
      "deviation_from_avg": 0.39,
      "deviation_pct": 15.9,
      "variance_indicator": "Higher*",
      "injury_status": "",
      "injury_weight": 1.0,
      "actual_shots": null,
      "hit_2plus": null,
      "hit_3plus": null,
      "game_id": 2025020694,
      "matchup": "WSH @ CHI"
    },
    {
      "player_id": 8483450,
      "player_name": "Ryan Greene",
      "position": "C",
      "team": "CHI",
      "opponent": "WSH",
      "is_home": true,
      "expected_shots": 2.16,
      "shots_std": 1.22,
      "prob_2plus": 0.634,
      "prob_3plus": 0.365,
      "prob_4plus": 0.172,
      "confidence": 0.801,
      "avg_toi_minutes": 17.3,
      "games_analyzed": 15,
      "historical_avg_shots": 1.73,
      "deviation_from_avg": 0.42,
      "deviation_pct": 24.3,
      "variance_indicator": "Higher*",
      "injury_status": "",
      "injury_weight": 1.0,
      "actual_shots": null,
      "hit_2plus": null,
      "hit_3plus": null,
      "game_id": 2025020694,
      "matchup": "WSH @ CHI"
    },
    {
      "player_id": 8477444,
      "player_name": "Andre Burakovsky",
      "position": "L",
      "team": "CHI",
      "opponent": "WSH",
      "is_home": true,
      "expected_shots": 1.63,
      "shots_std": 1.45,
      "prob_2plus": 0.458,
      "prob_3plus": 0.234,
      "prob_4plus": 0.106,
      "confidence": 0.763,
      "avg_toi_minutes": 17.3,
      "games_analyzed": 15,
      "historical_avg_shots": 1.4,
      "deviation_from_avg": 0.23,
      "deviation_pct": 16.4,
      "variance_indicator": "Volatile",
      "injury_status": "",
      "injury_weight": 1.0,
      "actual_shots": null,
      "hit_2plus": null,
      "hit_3plus": null,
      "game_id": 2025020694,
      "matchup": "WSH @ CHI"
    },
    {
      "player_id": 8481806,
      "player_name": "Louis Crevier",
      "position": "D",
      "team": "CHI",
      "opponent": "WSH",
      "is_home": true,
      "expected_shots": 1.62,
      "shots_std": 0.88,
      "prob_2plus": 0.482,
      "prob_3plus": 0.223,
      "prob_4plus": 0.082,
      "confidence": 0.573,
      "avg_toi_minutes": 18.1,
      "games_analyzed": 15,
      "historical_avg_shots": 1.93,
      "deviation_from_avg": -0.31,
      "deviation_pct": -16.0,
      "variance_indicator": "Lower*",
      "injury_status": "DTD",
      "injury_weight": 0.5,
      "actual_shots": null,
      "hit_2plus": null,
      "hit_3plus": null,
      "game_id": 2025020694,
      "matchup": "WSH @ CHI"
    },
    {
      "player_id": 8477987,
      "player_name": "Ryan Donato",
      "position": "C",
      "team": "CHI",
      "opponent": "WSH",
      "is_home": true,
      "expected_shots": 1.57,
      "shots_std": 1.78,
      "prob_2plus": 0.397,
      "prob_3plus": 0.228,
      "prob_4plus": 0.128,
      "confidence": 0.754,
      "avg_toi_minutes": 15.8,
      "games_analyzed": 15,
      "historical_avg_shots": 1.53,
      "deviation_from_avg": 0.03,
      "deviation_pct": 2.2,
      "variance_indicator": "Volatile",
      "injury_status": "",
      "injury_weight": 1.0,
      "actual_shots": null,
      "hit_2plus": null,
      "hit_3plus": null,
      "game_id": 2025020694,
      "matchup": "WSH @ CHI"
    },
    {
      "player_id": 8481624,
      "player_name": "Ilya Mikheyev",
      "position": "R",
      "team": "CHI",
      "opponent": "WSH",
      "is_home": true,
      "expected_shots": 1.54,
      "shots_std": 1.28,
      "prob_2plus": 0.449,
      "prob_3plus": 0.204,
      "prob_4plus": 0.076,
      "confidence": 0.54,
      "avg_toi_minutes": 17.2,
      "games_analyzed": 15,
      "historical_avg_shots": 1.73,
      "deviation_from_avg": -0.2,
      "deviation_pct": -11.3,
      "variance_indicator": "Volatile",
      "injury_status": "DTD",
      "injury_weight": 0.5,
      "actual_shots": null,
      "hit_2plus": null,
      "hit_3plus": null,
      "game_id": 2025020694,
      "matchup": "WSH @ CHI"
    },
    {
      "player_id": 8476882,
      "player_name": "Teuvo Teravainen",
      "position": "C",
      "team": "CHI",
      "opponent": "WSH",
      "is_home": true,
      "expected_shots": 1.53,
      "shots_std": 0.99,
      "prob_2plus": 0.453,
      "prob_3plus": 0.199,
      "prob_4plus": 0.07,
      "confidence": 0.782,
      "avg_toi_minutes": 17.1,
      "games_analyzed": 15,
      "historical_avg_shots": 1.47,
      "deviation_from_avg": 0.07,
      "deviation_pct": 4.5,
      "variance_indicator": "Volatile",
      "injury_status": "",
      "injury_weight": 1.0,
      "actual_shots": null,
      "hit_2plus": null,
      "hit_3plus": null,
      "game_id": 2025020694,
      "matchup": "WSH @ CHI"
    },
    {
      "player_id": 8479345,
      "player_name": "Jakob Chychrun",
      "position": "D",
      "team": "WSH",
      "opponent": "CHI",
      "is_home": false,
      "expected_shots": 2.65,
      "shots_std": 2.0,
      "prob_2plus": 0.678,
      "prob_3plus": 0.461,
      "prob_4plus": 0.286,
      "confidence": 0.774,
      "avg_toi_minutes": 23.2,
      "games_analyzed": 15,
      "historical_avg_shots": 3.47,
      "deviation_from_avg": -0.81,
      "deviation_pct": -23.5,
      "variance_indicator": "Volatile",
      "injury_status": "",
      "injury_weight": 1.0,
      "actual_shots": null,
      "hit_2plus": null,
      "hit_3plus": null,
      "game_id": 2025020694,
      "matchup": "WSH @ CHI"
    },
    {
      "player_id": 8471214,
      "player_name": "Alex Ovechkin",
      "position": "L",
      "team": "WSH",
      "opponent": "CHI",
      "is_home": false,
      "expected_shots": 2.65,
      "shots_std": 1.52,
      "prob_2plus": 0.741,
      "prob_3plus": 0.493,
      "prob_4plus": 0.274,
      "confidence": 0.811,
      "avg_toi_minutes": 17.8,
      "games_analyzed": 15,
      "historical_avg_shots": 2.8,
      "deviation_from_avg": -0.15,
      "deviation_pct": -5.5,
      "variance_indicator": "Variable",
      "injury_status": "",
      "injury_weight": 1.0,
      "actual_shots": null,
      "hit_2plus": null,
      "hit_3plus": null,
      "game_id": 2025020694,
      "matchup": "WSH @ CHI"
    },
    {
      "player_id": 8476880,
      "player_name": "Tom Wilson",
      "position": "R",
      "team": "WSH",
      "opponent": "CHI",
      "is_home": false,
      "expected_shots": 2.43,
      "shots_std": 2.51,
      "prob_2plus": 0.546,
      "prob_3plus": 0.377,
      "prob_4plus": 0.254,
      "confidence": 0.521,
      "avg_toi_minutes": 19.2,
      "games_analyzed": 15,
      "historical_avg_shots": 2.67,
      "deviation_from_avg": -0.24,
      "deviation_pct": -9.0,
      "variance_indicator": "Volatile",
      "injury_status": "DTD",
      "injury_weight": 0.5,
      "actual_shots": null,
      "hit_2plus": null,
      "hit_3plus": null,
      "game_id": 2025020694,
      "matchup": "WSH @ CHI"
    },
    {
      "player_id": 8478440,
      "player_name": "Dylan Strome",
      "position": "C",
      "team": "WSH",
      "opponent": "CHI",
      "is_home": false,
      "expected_shots": 2.11,
      "shots_std": 1.11,
      "prob_2plus": 0.624,
      "prob_3plus": 0.354,
      "prob_4plus": 0.164,
      "confidence": 0.823,
      "avg_toi_minutes": 18.9,
      "games_analyzed": 15,
      "historical_avg_shots": 2.33,
      "deviation_from_avg": -0.22,
      "deviation_pct": -9.4,
      "variance_indicator": "Variable",
      "injury_status": "",
      "injury_weight": 1.0,
      "actual_shots": null,
      "hit_2plus": null,
      "hit_3plus": null,
      "game_id": 2025020694,
      "matchup": "WSH @ CHI"
    },
    {
      "player_id": 8481656,
      "player_name": "Aliaksei Protas",
      "position": "C",
      "team": "WSH",
      "opponent": "CHI",
      "is_home": false,
      "expected_shots": 2.1,
      "shots_std": 1.52,
      "prob_2plus": 0.607,
      "prob_3plus": 0.349,
      "prob_4plus": 0.17,
      "confidence": 0.759,
      "avg_toi_minutes": 17.8,
      "games_analyzed": 15,
      "historical_avg_shots": 2.2,
      "deviation_from_avg": -0.1,
      "deviation_pct": -4.5,
      "variance_indicator": "Volatile",
      "injury_status": "",
      "injury_weight": 1.0,
      "actual_shots": null,
      "hit_2plus": null,
      "hit_3plus": null,
      "game_id": 2025020694,
      "matchup": "WSH @ CHI"
    },
    {
      "player_id": 8484186,
      "player_name": "Ryan Leonard",
      "position": "R",
      "team": "WSH",
      "opponent": "CHI",
      "is_home": false,
      "expected_shots": 2.05,
      "shots_std": 1.66,
      "prob_2plus": 0.565,
      "prob_3plus": 0.333,
      "prob_4plus": 0.175,
      "confidence": 0.739,
      "avg_toi_minutes": 15.5,
      "games_analyzed": 15,
      "historical_avg_shots": 2.27,
      "deviation_from_avg": -0.22,
      "deviation_pct": -9.6,
      "variance_indicator": "Volatile",
      "injury_status": "",
      "injury_weight": 1.0,
      "actual_shots": null,
      "hit_2plus": null,
      "hit_3plus": null,
      "game_id": 2025020694,
      "matchup": "WSH @ CHI"
    },
    {
      "player_id": 8478463,
      "player_name": "Anthony Beauvillier",
      "position": "L",
      "team": "WSH",
      "opponent": "CHI",
      "is_home": false,
      "expected_shots": 1.93,
      "shots_std": 1.39,
      "prob_2plus": 0.576,
      "prob_3plus": 0.305,
      "prob_4plus": 0.131,
      "confidence": 0.761,
      "avg_toi_minutes": 16.4,
      "games_analyzed": 15,
      "historical_avg_shots": 2.07,
      "deviation_from_avg": -0.13,
      "deviation_pct": -6.5,
      "variance_indicator": "Volatile",
      "injury_status": "",
      "injury_weight": 1.0,
      "actual_shots": null,
      "hit_2plus": null,
      "hit_3plus": null,
      "game_id": 2025020694,
      "matchup": "WSH @ CHI"
    },
    {
      "player_id": 8482088,
      "player_name": "Justin Sourdif",
      "position": "R",
      "team": "WSH",
      "opponent": "CHI",
      "is_home": false,
      "expected_shots": 1.85,
      "shots_std": 1.23,
      "prob_2plus": 0.553,
      "prob_3plus": 0.284,
      "prob_4plus": 0.117,
      "confidence": 0.773,
      "avg_toi_minutes": 17.0,
      "games_analyzed": 15,
      "historical_avg_shots": 1.67,
      "deviation_from_avg": 0.19,
      "deviation_pct": 11.2,
      "variance_indicator": "Volatile",
      "injury_status": "",
      "injury_weight": 1.0,
      "actual_shots": null,
      "hit_2plus": null,
      "hit_3plus": null,
      "game_id": 2025020694,
      "matchup": "WSH @ CHI"
    },
    {
      "player_id": 8481580,
      "player_name": "Connor McMichael",
      "position": "C",
      "team": "WSH",
      "opponent": "CHI",
      "is_home": false,
      "expected_shots": 1.66,
      "shots_std": 1.36,
      "prob_2plus": 0.485,
      "prob_3plus": 0.237,
      "prob_4plus": 0.097,
      "confidence": 0.764,
      "avg_toi_minutes": 18.1,
      "games_analyzed": 15,
      "historical_avg_shots": 1.47,
      "deviation_from_avg": 0.2,
      "deviation_pct": 13.5,
      "variance_indicator": "Volatile",
      "injury_status": "",
      "injury_weight": 1.0,
      "actual_shots": null,
      "hit_2plus": null,
      "hit_3plus": null,
      "game_id": 2025020694,
      "matchup": "WSH @ CHI"
    },
    {
      "player_id": 8482699,
      "player_name": "Dylan Guenther",
      "position": "R",
      "team": "UTA",
      "opponent": "STL",
      "is_home": true,
      "expected_shots": 3.29,
      "shots_std": 1.74,
      "prob_2plus": 0.836,
      "prob_3plus": 0.639,
      "prob_4plus": 0.417,
      "confidence": 0.822,
      "avg_toi_minutes": 17.1,
      "games_analyzed": 15,
      "historical_avg_shots": 3.2,
      "deviation_from_avg": 0.09,
      "deviation_pct": 2.8,
      "variance_indicator": "Variable",
      "injury_status": "",
      "injury_weight": 1.0,
      "actual_shots": null,
      "hit_2plus": null,
      "hit_3plus": null,
      "game_id": 2025020696,
      "matchup": "STL @ UTA"
    },
    {
      "player_id": 8477951,
      "player_name": "Nick Schmaltz",
      "position": "C",
      "team": "UTA",
      "opponent": "STL",
      "is_home": true,
      "expected_shots": 2.9,
      "shots_std": 2.28,
      "prob_2plus": 0.691,
      "prob_3plus": 0.495,
      "prob_4plus": 0.33,
      "confidence": 0.775,
      "avg_toi_minutes": 20.3,
      "games_analyzed": 15,
      "historical_avg_shots": 2.73,
      "deviation_from_avg": 0.17,
      "deviation_pct": 6.3,
      "variance_indicator": "Volatile",
      "injury_status": "",
      "injury_weight": 1.0,
      "actual_shots": null,
      "hit_2plus": null,
      "hit_3plus": null,
      "game_id": 2025020696,
      "matchup": "STL @ UTA"
    },
    {
      "player_id": 8479343,
      "player_name": "Clayton Keller",
      "position": "R",
      "team": "UTA",
      "opponent": "STL",
      "is_home": true,
      "expected_shots": 2.43,
      "shots_std": 1.19,
      "prob_2plus": 0.698,
      "prob_3plus": 0.438,
      "prob_4plus": 0.228,
      "confidence": 0.832,
      "avg_toi_minutes": 20.3,
      "games_analyzed": 15,
      "historical_avg_shots": 2.47,
      "deviation_from_avg": -0.04,
      "deviation_pct": -1.4,
      "variance_indicator": "Variable",
      "injury_status": "",
      "injury_weight": 1.0,
      "actual_shots": null,
      "hit_2plus": null,
      "hit_3plus": null,
      "game_id": 2025020696,
      "matchup": "STL @ UTA"
    },
    {
      "player_id": 8482175,
      "player_name": "JJ Peterka",
      "position": "R",
      "team": "UTA",
      "opponent": "STL",
      "is_home": true,
      "expected_shots": 2.09,
      "shots_std": 2.49,
      "prob_2plus": 0.463,
      "prob_3plus": 0.311,
      "prob_4plus": 0.209,
      "confidence": 0.752,
      "avg_toi_minutes": 17.9,
      "games_analyzed": 15,
      "historical_avg_shots": 2.07,
      "deviation_from_avg": 0.02,
      "deviation_pct": 1.0,
      "variance_indicator": "Volatile",
      "injury_status": "",
      "injury_weight": 1.0,
      "actual_shots": null,
      "hit_2plus": null,
      "hit_3plus": null,
      "game_id": 2025020696,
      "matchup": "STL @ UTA"
    },
    {
      "player_id": 8479410,
      "player_name": "Mikhail Sergachev",
      "position": "D",
      "team": "UTA",
      "opponent": "STL",
      "is_home": true,
      "expected_shots": 1.94,
      "shots_std": 1.16,
      "prob_2plus": 0.577,
      "prob_3plus": 0.307,
      "prob_4plus": 0.132,
      "confidence": 0.803,
      "avg_toi_minutes": 23.9,
      "games_analyzed": 15,
      "historical_avg_shots": 2.07,
      "deviation_from_avg": -0.13,
      "deviation_pct": -6.2,
      "variance_indicator": "Volatile",
      "injury_status": "",
      "injury_weight": 1.0,
      "actual_shots": null,
      "hit_2plus": null,
      "hit_3plus": null,
      "game_id": 2025020696,
      "matchup": "STL @ UTA"
    },
    {
      "player_id": 8480434,
      "player_name": "Sean Durzi",
      "position": "D",
      "team": "UTA",
      "opponent": "STL",
      "is_home": true,
      "expected_shots": 1.82,
      "shots_std": 1.16,
      "prob_2plus": 0.544,
      "prob_3plus": 0.276,
      "prob_4plus": 0.113,
      "confidence": 0.789,
      "avg_toi_minutes": 20.9,
      "games_analyzed": 15,
      "historical_avg_shots": 2.07,
      "deviation_from_avg": -0.24,
      "deviation_pct": -11.8,
      "variance_indicator": "Volatile",
      "injury_status": "",
      "injury_weight": 1.0,
      "actual_shots": null,
      "hit_2plus": null,
      "hit_3plus": null,
      "game_id": 2025020696,
      "matchup": "STL @ UTA"
    },
    {
      "player_id": 8478474,
      "player_name": "Lawson Crouse",
      "position": "L",
      "team": "UTA",
      "opponent": "STL",
      "is_home": true,
      "expected_shots": 1.65,
      "shots_std": 1.3,
      "prob_2plus": 0.488,
      "prob_3plus": 0.231,
      "prob_4plus": 0.088,
      "confidence": 0.77,
      "avg_toi_minutes": 17.3,
      "games_analyzed": 15,
      "historical_avg_shots": 1.47,
      "deviation_from_avg": 0.18,
      "deviation_pct": 12.5,
      "variance_indicator": "Volatile",
      "injury_status": "",
      "injury_weight": 1.0,
      "actual_shots": null,
      "hit_2plus": null,
      "hit_3plus": null,
      "game_id": 2025020696,
      "matchup": "STL @ UTA"
    },
    {
      "player_id": 8480849,
      "player_name": "Barrett Hayton",
      "position": "C",
      "team": "UTA",
      "opponent": "STL",
      "is_home": true,
      "expected_shots": 1.62,
      "shots_std": 1.99,
      "prob_2plus": 0.39,
      "prob_3plus": 0.237,
      "prob_4plus": 0.144,
      "confidence": 0.774,
      "avg_toi_minutes": 14.6,
      "games_analyzed": 15,
      "historical_avg_shots": 1.67,
      "deviation_from_avg": -0.05,
      "deviation_pct": -2.8,
      "variance_indicator": "Volatile",
      "injury_status": "",
      "injury_weight": 1.0,
      "actual_shots": null,
      "hit_2plus": null,
      "hit_3plus": null,
      "game_id": 2025020696,
      "matchup": "STL @ UTA"
    },
    {
      "player_id": 8479385,
      "player_name": "Jordan Kyrou",
      "position": "R",
      "team": "STL",
      "opponent": "UTA",
      "is_home": false,
      "expected_shots": 1.56,
      "shots_std": 1.65,
      "prob_2plus": 0.409,
      "prob_3plus": 0.225,
      "prob_4plus": 0.118,
      "confidence": 0.73,
      "avg_toi_minutes": 14.6,
      "games_analyzed": 15,
      "historical_avg_shots": 2.2,
      "deviation_from_avg": -0.64,
      "deviation_pct": -29.2,
      "variance_indicator": "Volatile",
      "injury_status": "",
      "injury_weight": 1.0,
      "actual_shots": null,
      "hit_2plus": null,
      "hit_3plus": null,
      "game_id": 2025020696,
      "matchup": "STL @ UTA"
    },
    {
      "player_id": 8478398,
      "player_name": "Kyle Connor",
      "position": "L",
      "team": "WPG",
      "opponent": "LAK",
      "is_home": true,
      "expected_shots": 2.25,
      "shots_std": 2.2,
      "prob_2plus": 0.543,
      "prob_3plus": 0.358,
      "prob_4plus": 0.227,
      "confidence": 0.77,
      "avg_toi_minutes": 21.6,
      "games_analyzed": 15,
      "historical_avg_shots": 3.47,
      "deviation_from_avg": -1.21,
      "deviation_pct": -35.0,
      "variance_indicator": "Volatile",
      "injury_status": "",
      "injury_weight": 1.0,
      "actual_shots": null,
      "hit_2plus": null,
      "hit_3plus": null,
      "game_id": 2025020695,
      "matchup": "LAK @ WPG"
    },
    {
      "player_id": 8476460,
      "player_name": "Mark Scheifele",
      "position": "C",
      "team": "WPG",
      "opponent": "LAK",
      "is_home": true,
      "expected_shots": 1.62,
      "shots_std": 2.13,
      "prob_2plus": 0.375,
      "prob_3plus": 0.235,
      "prob_4plus": 0.148,
      "confidence": 0.767,
      "avg_toi_minutes": 21.9,
      "games_analyzed": 15,
      "historical_avg_shots": 2.13,
      "deviation_from_avg": -0.51,
      "deviation_pct": -24.0,
      "variance_indicator": "Volatile",
      "injury_status": "",
      "injury_weight": 1.0,
      "actual_shots": null,
      "hit_2plus": null,
      "hit_3plus": null,
      "game_id": 2025020695,
      "matchup": "LAK @ WPG"
    },
    {
      "player_id": 8477960,
      "player_name": "Adrian Kempe",
      "position": "R",
      "team": "LAK",
      "opponent": "WPG",
      "is_home": false,
      "expected_shots": 2.37,
      "shots_std": 1.77,
      "prob_2plus": 0.642,
      "prob_3plus": 0.407,
      "prob_4plus": 0.23,
      "confidence": 0.766,
      "avg_toi_minutes": 18.6,
      "games_analyzed": 15,
      "historical_avg_shots": 2.47,
      "deviation_from_avg": -0.1,
      "deviation_pct": -4.1,
      "variance_indicator": "Volatile",
      "injury_status": "",
      "injury_weight": 1.0,
      "actual_shots": null,
      "hit_2plus": null,
      "hit_3plus": null,
      "game_id": 2025020695,
      "matchup": "LAK @ WPG"
    },
    {
      "player_id": 8477942,
      "player_name": "Kevin Fiala",
      "position": "L",
      "team": "LAK",
      "opponent": "WPG",
      "is_home": false,
      "expected_shots": 2.35,
      "shots_std": 1.19,
      "prob_2plus": 0.681,
      "prob_3plus": 0.418,
      "prob_4plus": 0.212,
      "confidence": 0.827,
      "avg_toi_minutes": 18.6,
      "games_analyzed": 15,
      "historical_avg_shots": 2.47,
      "deviation_from_avg": -0.11,
      "deviation_pct": -4.6,
      "variance_indicator": "Variable",
      "injury_status": "",
      "injury_weight": 1.0,
      "actual_shots": null,
      "hit_2plus": null,
      "hit_3plus": null,
      "game_id": 2025020695,
      "matchup": "LAK @ WPG"
    },
    {
      "player_id": 8482155,
      "player_name": "Alex Laferriere",
      "position": "R",
      "team": "LAK",
      "opponent": "WPG",
      "is_home": false,
      "expected_shots": 2.33,
      "shots_std": 2.12,
      "prob_2plus": 0.576,
      "prob_3plus": 0.379,
      "prob_4plus": 0.237,
      "confidence": 0.772,
      "avg_toi_minutes": 17.3,
      "games_analyzed": 15,
      "historical_avg_shots": 2.93,
      "deviation_from_avg": -0.6,
      "deviation_pct": -20.5,
      "variance_indicator": "Volatile",
      "injury_status": "",
      "injury_weight": 1.0,
      "actual_shots": null,
      "hit_2plus": null,
      "hit_3plus": null,
      "game_id": 2025020695,
      "matchup": "LAK @ WPG"
    },
    {
      "player_id": 8477998,
      "player_name": "Warren Foegele",
      "position": "L",
      "team": "LAK",
      "opponent": "WPG",
      "is_home": false,
      "expected_shots": 1.97,
      "shots_std": 1.82,
      "prob_2plus": 0.517,
      "prob_3plus": 0.311,
      "prob_4plus": 0.175,
      "confidence": 0.771,
      "avg_toi_minutes": 15.2,
      "games_analyzed": 15,
      "historical_avg_shots": 2.2,
      "deviation_from_avg": -0.23,
      "deviation_pct": -10.4,
      "variance_indicator": "Volatile",
      "injury_status": "",
      "injury_weight": 1.0,
      "actual_shots": null,
      "hit_2plus": null,
      "hit_3plus": null,
      "game_id": 2025020695,
      "matchup": "LAK @ WPG"
    },
    {
      "player_id": 8482124,
      "player_name": "Quinton Byfield",
      "position": "R",
      "team": "LAK",
      "opponent": "WPG",
      "is_home": false,
      "expected_shots": 1.7,
      "shots_std": 1.33,
      "prob_2plus": 0.503,
      "prob_3plus": 0.246,
      "prob_4plus": 0.098,
      "confidence": 0.773,
      "avg_toi_minutes": 19.7,
      "games_analyzed": 15,
      "historical_avg_shots": 1.93,
      "deviation_from_avg": -0.23,
      "deviation_pct": -11.8,
      "variance_indicator": "Volatile",
      "injury_status": "",
      "injury_weight": 1.0,
      "actual_shots": null,
      "hit_2plus": null,
      "hit_3plus": null,
      "game_id": 2025020695,
      "matchup": "LAK @ WPG"
    },
    {
      "player_id": 8474563,
      "player_name": "Drew Doughty",
      "position": "D",
      "team": "LAK",
      "opponent": "WPG",
      "is_home": false,
      "expected_shots": 1.6,
      "shots_std": 1.36,
      "prob_2plus": 0.462,
      "prob_3plus": 0.223,
      "prob_4plus": 0.092,
      "confidence": 0.779,
      "avg_toi_minutes": 23.1,
      "games_analyzed": 15,
      "historical_avg_shots": 1.87,
      "deviation_from_avg": -0.27,
      "deviation_pct": -14.3,
      "variance_indicator": "Volatile",
      "injury_status": "",
      "injury_weight": 1.0,
      "actual_shots": null,
      "hit_2plus": null,
      "hit_3plus": null,
      "game_id": 2025020695,
      "matchup": "LAK @ WPG"
    },
    {
      "player_id": 8482730,
      "player_name": "Brandt Clarke",
      "position": "D",
      "team": "LAK",
      "opponent": "WPG",
      "is_home": false,
      "expected_shots": 1.58,
      "shots_std": 1.58,
      "prob_2plus": 0.425,
      "prob_3plus": 0.228,
      "prob_4plus": 0.115,
      "confidence": 0.769,
      "avg_toi_minutes": 18.4,
      "games_analyzed": 15,
      "historical_avg_shots": 1.93,
      "deviation_from_avg": -0.35,
      "deviation_pct": -18.2,
      "variance_indicator": "Volatile",
      "injury_status": "",
      "injury_weight": 1.0,
      "actual_shots": null,
      "hit_2plus": null,
      "hit_3plus": null,
      "game_id": 2025020695,
      "matchup": "LAK @ WPG"
    }
  ]
}